pavlok/__init__.py
pavlok/constants.py
pavlok/main.py
pavlok-0.2.0.dist-info/LICENSE
pavlok-0.2.0.dist-info/METADATA
pavlok-0.2.0.dist-info/WHEEL
pavlok-0.2.0.dist-info/top_level.txt
pavlok-0.2.0.dist-info/RECORD
