Metadata-Version: 2.1
Name: pavlok
Version: 0.2.0
Summary: Pavlok python client
Home-page: https://github.com/Pavlok/pavlok-python-client
Author: Maneesh Sethi
Author-email: maneesh@pavlok.com
License: UNKNOWN
Project-URL: Bug Tracker, https://github.com/Pavlok/pavlok-python-client/issues
Platform: UNKNOWN
Classifier: Programming Language :: Python :: 3
Classifier: License :: OSI Approved :: MIT License
Classifier: Operating System :: OS Independent
Requires-Python: >=3.8
License-File: LICENSE
Requires-Dist: Authlib (==0.15.4)
Requires-Dist: fastapi (==0.68.1)
Requires-Dist: pydantic (==1.8.2)
Requires-Dist: starlette (==0.14.2)
Requires-Dist: uvicorn (==0.15.0)
